MANIFEST.in
README.md
pyproject.toml
fastapi_auth/__init__.py
fastapi_auth/auth_config.py
fastapi_auth/auth_routes.py
fastapi_auth/authenticator_registry.py
fastapi_auth/demo_app.py
fastapi_auth/dependencies.py
fastapi_auth/jinja2_templates.py
fastapi_auth/logger.py
fastapi_auth/permissions.py
fastapi_auth/py.typed
fastapi_auth/roles.py
fastapi_auth/user_cmd.py
fastapi_auth/user_management_sqlobject.py
fastapi_auth/users.py
fastapi_auth/templates/base.html
fastapi_auth/templates/demo.html
fastapi_auth/templates/login.html
images/logged-in.png
images/login.png
static/bootstrap-5.3.3-dist/css/bootstrap-grid.css
static/bootstrap-5.3.3-dist/css/bootstrap-grid.css.map
static/bootstrap-5.3.3-dist/css/bootstrap-grid.min.css
static/bootstrap-5.3.3-dist/css/bootstrap-grid.min.css.map
static/bootstrap-5.3.3-dist/css/bootstrap-grid.rtl.css
static/bootstrap-5.3.3-dist/css/bootstrap-grid.rtl.css.map
static/bootstrap-5.3.3-dist/css/bootstrap-grid.rtl.min.css
static/bootstrap-5.3.3-dist/css/bootstrap-grid.rtl.min.css.map
static/bootstrap-5.3.3-dist/css/bootstrap-reboot.css
static/bootstrap-5.3.3-dist/css/bootstrap-reboot.css.map
static/bootstrap-5.3.3-dist/css/bootstrap-reboot.min.css
static/bootstrap-5.3.3-dist/css/bootstrap-reboot.min.css.map
static/bootstrap-5.3.3-dist/css/bootstrap-reboot.rtl.css
static/bootstrap-5.3.3-dist/css/bootstrap-reboot.rtl.css.map
static/bootstrap-5.3.3-dist/css/bootstrap-reboot.rtl.min.css
static/bootstrap-5.3.3-dist/css/bootstrap-reboot.rtl.min.css.map
static/bootstrap-5.3.3-dist/css/bootstrap-utilities.css
static/bootstrap-5.3.3-dist/css/bootstrap-utilities.css.map
static/bootstrap-5.3.3-dist/css/bootstrap-utilities.min.css
static/bootstrap-5.3.3-dist/css/bootstrap-utilities.min.css.map
static/bootstrap-5.3.3-dist/css/bootstrap-utilities.rtl.css
static/bootstrap-5.3.3-dist/css/bootstrap-utilities.rtl.css.map
static/bootstrap-5.3.3-dist/css/bootstrap-utilities.rtl.min.css
static/bootstrap-5.3.3-dist/css/bootstrap-utilities.rtl.min.css.map
zopyx_fastapi_auth.egg-info/PKG-INFO
zopyx_fastapi_auth.egg-info/SOURCES.txt
zopyx_fastapi_auth.egg-info/dependency_links.txt
zopyx_fastapi_auth.egg-info/entry_points.txt
zopyx_fastapi_auth.egg-info/requires.txt
zopyx_fastapi_auth.egg-info/top_level.txt