Metadata-Version: 2.1
Name: zopyx-fastapi-auth
Version: 0.2.3
Summary: FastAPI authentication and authorization
Author-email: Andreas Jung <info@zopyx.com>
Project-URL: homepage, https://github.com/zopyx/fastapi-auth
Classifier: Programming Language :: Python :: 3.10
Classifier: Programming Language :: Python :: 3.11
Classifier: Programming Language :: Python :: 3.12
Requires-Dist: fastapi
Requires-Dist: pydantic
Requires-Dist: pydantic-settings
Requires-Dist: uvicorn
Requires-Dist: markdown
Requires-Dist: starlette-session
Requires-Dist: loguru
Requires-Dist: bcrypt
Requires-Dist: jinja2
Requires-Dist: sqlmodel
Requires-Dist: rich
Requires-Dist: python-multipart
Requires-Dist: typer
Requires-Dist: typeguard
Provides-Extra: dev
Requires-Dist: tox; extra == "dev"
Requires-Dist: pytest; extra == "dev"
Requires-Dist: ruff; extra == "dev"
Requires-Dist: twine; extra == "dev"
Requires-Dist: build; extra == "dev"
Requires-Dist: pytest-cov; extra == "dev"
